logarithma/__init__.py
logarithma/algorithms/__init__.py
logarithma/algorithms/shortest_path/__init__.py
logarithma/algorithms/shortest_path/dijkstra.py
logarithma/algorithms/traversal/__init__.py
logarithma/algorithms/traversal/bfs.py
logarithma/algorithms/traversal/dfs.py
logarithma/utils/__init__.py
logarithma/utils/converters.py
logarithma/utils/graph_generators.py
logarithma/utils/metrics.py
logarithma/utils/validators.py
logarithma/visualization/__init__.py
logarithma-0.2.0.dist-info/licenses/LICENSE
logarithma-0.2.0.dist-info/METADATA
logarithma-0.2.0.dist-info/WHEEL
logarithma-0.2.0.dist-info/top_level.txt
logarithma-0.2.0.dist-info/RECORD
