Metadata-Version: 2.4
Name: logarithma
Version: 0.2.0
Summary: High-performance graph algorithms library featuring advanced shortest path algorithms
Author-email: Can AKYILDIRIM <akyildirimcan@gmail.com>
License: MIT License
Project-URL: Homepage, https://github.com/softdevcan/logarithma
Project-URL: Repository, https://github.com/softdevcan/logarithma
Project-URL: Bug Tracker, https://github.com/softdevcan/logarithma/issues
Keywords: graph,algorithms,shortest-path,optimization
Classifier: Development Status :: 3 - Alpha
Classifier: Programming Language :: Python :: 3
Classifier: Programming Language :: Python :: 3.8
Classifier: Programming Language :: Python :: 3.9
Classifier: Programming Language :: Python :: 3.10
Classifier: Programming Language :: Python :: 3.11
Classifier: Programming Language :: Python :: 3.12
Classifier: License :: OSI Approved :: MIT License
Classifier: Topic :: Scientific/Engineering :: Mathematics
Requires-Python: >=3.8
License-File: LICENSE
Requires-Dist: numpy>=1.20.0
Requires-Dist: networkx>=2.6
Provides-Extra: dev
Requires-Dist: pytest>=7.0; extra == "dev"
Requires-Dist: black>=22.0; extra == "dev"
Requires-Dist: isort>=5.0; extra == "dev"
Requires-Dist: flake8>=5.0; extra == "dev"
Provides-Extra: viz
Requires-Dist: matplotlib>=3.5; extra == "viz"
Requires-Dist: plotly>=5.0; extra == "viz"
Dynamic: license-file
